puri/__init__.py
puri/hello.py
puri-0.0.3.dist-info/LICENSE
puri-0.0.3.dist-info/METADATA
puri-0.0.3.dist-info/WHEEL
puri-0.0.3.dist-info/top_level.txt
puri-0.0.3.dist-info/RECORD
