Metadata-Version: 2.1
Name: puri
Version: 0.0.3
Summary: A personal tools for make everythings easy !
Home-page: https://github.com/suakow/puri
Author: Puri Phakmongkol
Author-email: puri.pmk@gmail.com
License: UNKNOWN
Platform: UNKNOWN
Classifier: Programming Language :: Python :: 3
Classifier: License :: OSI Approved :: MIT License
Classifier: Operating System :: OS Independent
Requires-Python: >=3.6
